bear_gui_tools/__init__.py
bear_gui_tools/__main__.py
bear_gui_tools/_settings.py
bear_gui_tools/_types.py
bear_gui_tools/config.py
bear_gui_tools/py.typed
bear_gui_tools/qt_app.py
bear_gui_tools/qt_color_picker.py
bear_gui_tools/qt_file_handler.py
bear_gui_tools/qt_input_dialog.py
bear_gui_tools/_internal/__init__.py
bear_gui_tools/_internal/_info.py
bear_gui_tools/_internal/_version.py
bear_gui_tools/_internal/_version.pyi
bear_gui_tools/_internal/cli.py
bear_gui_tools/_internal/debug.py
bear_gui_tools/di/__init__.py
bear_gui_tools/di/container.py
bear_gui_tools-0.1.4.dist-info/METADATA
bear_gui_tools-0.1.4.dist-info/WHEEL
bear_gui_tools-0.1.4.dist-info/entry_points.txt
bear_gui_tools-0.1.4.dist-info/RECORD
