Metadata-Version: 2.4
Name: bear-gui-tools
Version: 0.1.4
Summary: A set of GUI tools for Bear Projects
Author-email: chaz <bright.lid5647@fastmail.com>
Requires-Python: >=3.13
Requires-Dist: bear-dereth>=0.1.2
Requires-Dist: dependency-injector>=4.48.1
Requires-Dist: pydantic>=2.11.5
Requires-Dist: pyqt6>=6.9.1
Requires-Dist: rich>=14.1.0
Requires-Dist: typer>=0.16.0
